caliber/README.md
caliber/__init__.py
caliber/binary_classification/__init__.py
caliber/binary_classification/base.py
caliber/binary_classification/checks_mixin.py
caliber/binary_classification/pred_from_probs_mixin.py
caliber/binary_classification/binning/__init__.py
caliber/binary_classification/binning/base.py
caliber/binary_classification/binning/histogram_binning/__init__.py
caliber/binary_classification/binning/histogram_binning/base.py
caliber/binary_classification/binning/histogram_binning/smooth.py
caliber/binary_classification/binning/isotonic_regression/__init__.py
caliber/binary_classification/binning/isotonic_regression/base.py
caliber/binary_classification/binning/iterative_binning/__init__.py
caliber/binary_classification/binning/iterative_binning/base.py
caliber/binary_classification/constant_shift/__init__.py
caliber/binary_classification/constant_shift/model_bias/__init__.py
caliber/binary_classification/constant_shift/model_bias/base.py
caliber/binary_classification/group_conditional_unbiased/base.py
caliber/binary_classification/iterative_fitting/base.py
caliber/binary_classification/metrics/__init__.py
caliber/binary_classification/metrics/asce.py
caliber/binary_classification/metrics/bias.py
caliber/binary_classification/metrics/ece.py
caliber/binary_classification/metrics/focal_loss.py
caliber/binary_classification/metrics/knee_distance.py
caliber/binary_classification/metrics/precrec_error.py
caliber/binary_classification/metrics/rates.py
caliber/binary_classification/minimizing/__init__.py
caliber/binary_classification/minimizing/base.py
caliber/binary_classification/minimizing/linear_scaling/__init__.py
caliber/binary_classification/minimizing/linear_scaling/base.py
caliber/binary_classification/minimizing/linear_scaling/calibration/__init__.py
caliber/binary_classification/minimizing/linear_scaling/calibration/asce_linear_scaling.py
caliber/binary_classification/minimizing/linear_scaling/calibration/base.py
caliber-0.1.24.dist-info/METADATA
caliber-0.1.24.dist-info/WHEEL
caliber-0.1.24.dist-info/licenses/LICENSE
caliber-0.1.24.dist-info/RECORD
