Metadata-Version: 2.4
Name: caliber
Version: 0.1.24
Summary: Add your description here
License-File: LICENSE
Requires-Python: <3.12,>=3.10
Requires-Dist: absolufy-imports>=0.3.1
Requires-Dist: matplotlib>=3.9.4
Requires-Dist: numpy>=2.0.2
Requires-Dist: pandas>=2.2.3
Requires-Dist: pre-commit>=4.2.0
Requires-Dist: pytest-cov>=6.1.0
Requires-Dist: pytest>=8.3.5
Requires-Dist: scikit-learn>=1.6.1
Requires-Dist: scipy>=1.13.1
Requires-Dist: tabulate>=0.9.0
Requires-Dist: tqdm>=4.67.1
Requires-Dist: xgboost>=2.1.4
Provides-Extra: docs
Requires-Dist: furo>=2024.8.6; extra == 'docs'
Requires-Dist: sphinx-autodoc-typehints>=2.3.0; extra == 'docs'
Requires-Dist: sphinx-gallery>=0.19.0; extra == 'docs'
Requires-Dist: sphinx>=7.4.7; extra == 'docs'
Provides-Extra: torch
Requires-Dist: torch>=2.6.0; extra == 'torch'
Requires-Dist: torchvision>=0.21.0; extra == 'torch'
